setup.py
generic_erp/__init__.py
generic_erp.egg-info/PKG-INFO
generic_erp.egg-info/SOURCES.txt
generic_erp.egg-info/dependency_links.txt
generic_erp.egg-info/top_level.txt
generic_erp/document/__init__.py
generic_erp/document/document.py
generic_erp/document/invoice.py
generic_erp/document/invoice_line.py
generic_erp/document/stock_move.py
generic_erp/document/stock_picking.py
generic_erp/partner/__init__.py
generic_erp/partner/partner.py
generic_erp/partner/vat.py
generic_erp/tax/__init__.py
generic_erp/tax/tax.py