Metadata-Version: 1.1
Name: generic-erp
Version: 1.0.2
Summary: Generic ERP
Home-page: UNKNOWN
Author: BLUEORANGE GROUP
Author-email: daniel@blueorange.com.ar
License: UNKNOWN
Keywords: Generic ERP
Platform: UNKNOWN
Classifier: Development Status :: 4 - Beta
Classifier: Intended Audience :: Developers
Classifier: Topic :: Software Development
Classifier: Programming Language :: Python :: 2.7
